README.md
setup.py
Flask_PG_Extras.egg-info/PKG-INFO
Flask_PG_Extras.egg-info/SOURCES.txt
Flask_PG_Extras.egg-info/dependency_links.txt
Flask_PG_Extras.egg-info/entry_points.txt
Flask_PG_Extras.egg-info/not-zip-safe
Flask_PG_Extras.egg-info/requires.txt
Flask_PG_Extras.egg-info/top_level.txt
flask_pg_extras/__init__.py
flask_pg_extras/cli.py
flask_pg_extras/queries/__init__.py
flask_pg_extras/queries/extensions.py
flask_pg_extras/queries/index_size.py
flask_pg_extras/queries/index_unused.py
flask_pg_extras/queries/queries_active_locks.py
flask_pg_extras/queries/queries_blocking.py
flask_pg_extras/queries/queries_long_running.py
flask_pg_extras/queries/queries_outliers.py
flask_pg_extras/queries/queries_popular.py
flask_pg_extras/queries/table_bloat.py
flask_pg_extras/queries/table_cache_hit.py
flask_pg_extras/queries/table_est_row_count.py
flask_pg_extras/queries/table_index_size.py
flask_pg_extras/queries/table_index_usage.py
flask_pg_extras/queries/table_seq_scans.py
flask_pg_extras/queries/table_size.py
flask_pg_extras/queries/total_cache_hit.py
flask_pg_extras/queries/total_index_size.py
flask_pg_extras/queries/total_table_size.py
flask_pg_extras/queries/vacuum_stats.py